{
  "comment": "Local seed playlist for VPBD ASR acceptance. This is intentionally incomplete: L-stage release acceptance still requires the full 20-track category coverage and manual scores.",
  "runtime_overrides": {
    "lyrics_alignment.enabled": true,
    "lyrics_alignment.provider": "cli",
    "lyrics_alignment.strict": false,
    "fire_red.cli.executable": "scripts/fireredasr2s_worker.py",
    "fire_red.cli.timeout_s": 180.0
  },
  "tracks": [
    {
      "id": "local_smoke_01",
      "title": "local-smoke-zh-01",
      "category": "chinese_ballad",
      "path": "input/local-smoke-zh-01.mp3"
    },
    {
      "id": "local_smoke_02",
      "title": "local-smoke-en-01",
      "category": "english_pop",
      "path": "input/local-smoke-en-01.mp3"
    },
    {
      "id": "local_smoke_03",
      "title": "local-smoke-en-02",
      "category": "english_pop",
      "path": "input/local-smoke-en-02.mp3"
    },
    {
      "id": "local_smoke_04",
      "title": "local-smoke-folk-01",
      "category": "folk_low_dynamic",
      "path": "input/local-smoke-folk-01.mp3"
    },
    {
      "id": "local_smoke_05",
      "title": "local-smoke-folk-02",
      "category": "folk_low_dynamic",
      "path": "input/local-smoke-folk-02.mp3"
    }
  ]
}
